{
  "board": "FBISE",
  "classNo": 9,
  "chapter": 2,
  "isSpecial": false,
  "partNo": {
    "exercise": "2.2",
    "questionNo": 2,
    "part": 0
  },
  "questionType": "eqs",
  "status": "unlocked",
  "free": false,
  "filename": "fbise_cl_9_ch_2_ex_2.2_q_2_pt_0",
  "eqs": [],
  "grid": {
    "rows": [],
    "_id": "6522e0f785282ad77fd33b37",
    "global": {
      "bgColor": "#293544",
      "fontSize": 1,
      "padding": 1,
      "margin": 1,
      "cellBorderColor": "#e52222",
      "cellFontColor": "white",
      "showGrid": false,
      "gridColor": "#384556",
      "_id": "6522e0f785282ad77fd33b38"
    },
    "sp": [],
    "fs": []
  }
}